Metadata-Version: 1.1
Name: pysegbase
Version: 1.2.45
Summary: Graph Cut based 3D segmentation with editor
Home-page: https://github.com/mjirik/pyseg_base
Author: Miroslav Jirik and Vladimir Lukes
Author-email: miroslav.jirik@gmail.com
License: MIT
Keywords: Graph-Cut segmentation 3D editor
Platform: UNKNOWN
Classifier: Development Status :: 3 - Alpha
Classifier: Intended Audience :: Developers
Classifier: Topic :: Scientific/Engineering :: Bio-Informatics
Classifier: License :: OSI Approved :: BSD License
Classifier: Programming Language :: Python :: 2
Classifier: Programming Language :: Python :: 2.7
Classifier: Programming Language :: Python :: 3
Classifier: Programming Language :: Python :: 3.4
Classifier: Programming Language :: Python :: 3.5
